zokrates_pycrypto/__init__.py
zokrates_pycrypto/babyjubjub.py
zokrates_pycrypto/cli_zokrates.py
zokrates_pycrypto/eddsa.py
zokrates_pycrypto/field.py
zokrates_pycrypto/gadgets/__init__.py
zokrates_pycrypto/gadgets/pedersenHasher.py
zokrates_pycrypto/merkletree.py
zokrates_pycrypto/numbertheory.py
zokrates_pycrypto/optimised_scalar_mul.py
zokrates_pycrypto/utils.py
zokrates_pycrypto-0.2.0.dist-info/WHEEL
zokrates_pycrypto-0.2.0.dist-info/METADATA
zokrates_pycrypto-0.2.0.dist-info/RECORD
